{
    "נושא 4": "תחביבים ופעילויות פנאי",
    "סרטונים": [
      {
        "video_number": 1,
        "title": "תחביבים",
        "word": "Photography",
        "translation": "צילום",
        "examples": [
          {
            "sentence": "**Photography** is his favorite hobby.",
            "translation": "צילום הוא התחביב המועדף עליו."
          },
          {
            "sentence": "She enjoys **photography** in her free time.",
            "translation": "היא נהנית לעסוק בצילום בזמנה הפנוי."
          },
          {
            "sentence": "**Photography** captures moments.",
            "translation": "צילום לוכד רגעים."
          }
        ],
        "call_to_action": "שתפו בתגובות תמונה שצילמתם באנגלית!"
      },
      {
        "video_number": 2,
        "title": "תחביבים",
        "word": "Gardening",
        "translation": "גינון",
        "examples": [
          {
            "sentence": "She enjoys **gardening** on weekends.",
            "translation": "היא נהנית לעסוק בגינון בסופי שבוע."
          },
          {
            "sentence": "**Gardening** relaxes the mind.",
            "translation": "גינון מרגיע את הנפש."
          },
          {
            "sentence": "He grows vegetables through **gardening**.",
            "translation": "הוא מגדל ירקות באמצעות גינון."
          }
        ],
        "call_to_action": "כתבו בתגובות אם יש לכם גינה באנגלית!"
      },
      {
        "video_number": 3,
        "title": "תחביבים",
        "word": "Hiking",
        "translation": "טיול רגלי",
        "examples": [
          {
            "sentence": "They go **hiking** every summer.",
            "translation": "הם יוצאים לטיול רגלי כל קיץ."
          },
          {
            "sentence": "**Hiking** is good exercise.",
            "translation": "טיול רגלי הוא פעילות גופנית טובה."
          },
          {
            "sentence": "She bought new boots for **hiking**.",
            "translation": "היא קנתה מגפיים חדשים לטיול רגלי."
          }
        ],
        "call_to_action": "שתפו בתגובות איפה אתם אוהבים לטייל באנגלית!"
      },
      {
        "video_number": 4,
        "title": "תחביבים",
        "word": "Cooking",
        "translation": "בישול",
        "examples": [
          {
            "sentence": "**Cooking** is both fun and useful.",
            "translation": "בישול הוא גם כיף וגם שימושי."
          },
          {
            "sentence": "He is learning **cooking** from his mother.",
            "translation": "הוא לומד בישול מאמו."
          },
          {
            "sentence": "**Cooking** classes are popular.",
            "translation": "שיעורי בישול פופולריים."
          }
        ],
        "call_to_action": "כתבו בתגובות מה המנה שאתם אוהבים לבשל באנגלית!"
      },
      {
        "video_number": 5,
        "title": "תחביבים",
        "word": "Dancing",
        "translation": "ריקוד",
        "examples": [
          {
            "sentence": "They are learning **dancing** together.",
            "translation": "הם לומדים לרקוד יחד."
          },
          {
            "sentence": "**Dancing** is a great way to exercise.",
            "translation": "ריקוד הוא דרך מצוינת להתעמל."
          },
          {
            "sentence": "She enjoys **dancing** at parties.",
            "translation": "היא נהנית לרקוד במסיבות."
          }
        ],
        "call_to_action": "שתפו בתגובות איזה סגנון ריקוד אתם אוהבים באנגלית!"
      },
      {
        "video_number": 6,
        "title": "תחביבים",
        "word": "Reading",
        "translation": "קריאה",
        "examples": [
          {
            "sentence": "**Reading** expands your knowledge.",
            "translation": "קריאה מרחיבה את הידע שלך."
          },
          {
            "sentence": "He spends hours **reading** books.",
            "translation": "הוא מבלה שעות בקריאת ספרים."
          },
          {
            "sentence": "**Reading** is her favorite pastime.",
            "translation": "קריאה היא הבילוי המועדף עליה."
          }
        ],
        "call_to_action": "שתפו בתגובות איזה ספר אתם קוראים עכשיו באנגלית!"
      },
      {
        "video_number": 7,
        "title": "תחביבים",
        "word": "Fishing",
        "translation": "דיג",
        "examples": [
          {
            "sentence": "He goes **fishing** on the lake.",
            "translation": "הוא הולך לדוג באגם."
          },
          {
            "sentence": "**Fishing** requires patience.",
            "translation": "דיג דורש סבלנות."
          },
          {
            "sentence": "They enjoy **fishing** together.",
            "translation": "הם נהנים לדוג יחד."
          }
        ],
        "call_to_action": "כתבו בתגובות אם ניסיתם לדוג באנגלית!"
      },
      {
        "video_number": 8,
        "title": "תחביבים",
        "word": "Knitting",
        "translation": "סריגה",
        "examples": [
          {
            "sentence": "**Knitting** is a creative hobby.",
            "translation": "סריגה היא תחביב יצירתי."
          },
          {
            "sentence": "She made a scarf by **knitting**.",
            "translation": "היא הכינה צעיף באמצעות סריגה."
          },
          {
            "sentence": "**Knitting** helps her relax.",
            "translation": "סריגה עוזרת לה להירגע."
          }
        ],
        "call_to_action": "שתפו בתגובות אם אתם אוהבים ליצור דברים באנגלית!"
      },
      {
        "video_number": 9,
        "title": "תחביבים",
        "word": "Painting",
        "translation": "ציור",
        "examples": [
          {
            "sentence": "He enjoys **painting** landscapes.",
            "translation": "הוא נהנה לצייר נופים."
          },
          {
            "sentence": "**Painting** allows expression.",
            "translation": "ציור מאפשר ביטוי."
          },
          {
            "sentence": "She took a **painting** class.",
            "translation": "היא לקחה שיעור ציור."
          }
        ],
        "call_to_action": "כתבו בתגובות מה אתם אוהבים לצייר באנגלית!"
      },
      {
        "video_number": 10,
        "title": "תחביבים",
        "word": "Cooking",
        "translation": "בישול",
        "examples": [
          {
            "sentence": "**Cooking** new recipes is fun.",
            "translation": "בישול מתכונים חדשים הוא כיף."
          },
          {
            "sentence": "He watches **cooking** shows on TV.",
            "translation": "הוא צופה בתוכניות בישול בטלוויזיה."
          },
          {
            "sentence": "**Cooking** brings people together.",
            "translation": "בישול מקרב בין אנשים."
          }
        ],
        "call_to_action": "שתפו בתגובות מתכון שאתם אוהבים באנגלית!"
      },
      {
        "video_number": 11,
        "title": "תחביבים",
        "word": "Cycling",
        "translation": "רכיבה על אופניים",
        "examples": [
          {
            "sentence": "**Cycling** is good for health.",
            "translation": "רכיבה על אופניים טובה לבריאות."
          },
          {
            "sentence": "They go **cycling** every morning.",
            "translation": "הם הולכים לרכוב על אופניים כל בוקר."
          },
          {
            "sentence": "He bought a new **cycling** helmet.",
            "translation": "הוא קנה קסדת רכיבה חדשה."
          }
        ],
        "call_to_action": "כתבו בתגובות איפה אתם אוהבים לרכוב באנגלית!"
      },
      {
        "video_number": 12,
        "title": "תחביבים",
        "word": "Writing",
        "translation": "כתיבה",
        "examples": [
          {
            "sentence": "**Writing** helps express thoughts.",
            "translation": "כתיבה עוזרת להביע מחשבות."
          },
          {
            "sentence": "She is **writing** a novel.",
            "translation": "היא כותבת רומן."
          },
          {
            "sentence": "He enjoys **writing** poetry.",
            "translation": "הוא נהנה לכתוב שירה."
          }
        ],
        "call_to_action": "שתפו בתגובות אם אתם כותבים באנגלית!"
      },
      {
        "video_number": 13,
        "title": "תחביבים",
        "word": "Cooking",
        "translation": "בישול",
        "examples": [
          {
            "sentence": "They are hosting a **cooking** class.",
            "translation": "הם מארחים שיעור בישול."
          },
          {
            "sentence": "She loves **cooking** for her family.",
            "translation": "היא אוהבת לבשל למשפחתה."
          },
          {
            "sentence": "**Cooking** can be an art.",
            "translation": "בישול יכול להיות אמנות."
          }
        ],
        "call_to_action": "שתפו בתגובות איזה מטבח אתם אוהבים באנגלית!"
      },
      {
        "video_number": 14,
        "title": "תחביבים",
        "word": "Traveling",
        "translation": "נסיעות",
        "examples": [
          {
            "sentence": "**Traveling** broadens the mind.",
            "translation": "נסיעות מרחיבות את האופקים."
          },
          {
            "sentence": "They are **traveling** to new countries.",
            "translation": "הם נוסעים למדינות חדשות."
          },
          {
            "sentence": "She enjoys **traveling** alone.",
            "translation": "היא נהנית לנסוע לבד."
          }
        ],
        "call_to_action": "כתבו בתגובות לאן הייתם רוצים לנסוע באנגלית!"
      },
      {
        "video_number": 15,
        "title": "תחביבים",
        "word": "Swimming",
        "translation": "שחייה",
        "examples": [
          {
            "sentence": "**Swimming** is great exercise.",
            "translation": "שחייה היא פעילות גופנית מצוינת."
          },
          {
            "sentence": "He goes **swimming** every weekend.",
            "translation": "הוא הולך לשחות כל סוף שבוע."
          },
          {
            "sentence": "She teaches **swimming** to children.",
            "translation": "היא מלמדת שחייה לילדים."
          }
        ],
        "call_to_action": "שתפו בתגובות אם אתם אוהבים לשחות באנגלית!"
      }
    ]
  }
  