{
  "video_title": "הַשָּׁתִיל הַקָּטָן",
  "language_level": "קַל",
  "story_type": "אַלְגוֹרְיָה עַל הַטֶּבַע",
  "story": {
    "title": "הַשָּׁתִיל הַקָּטָן",
    "text": [
      {
        "english": "A small sapling was impatient.",
        "hebrew": "שָּׁתִיל קָטָן הָיָה חֲסַר סַבְלָנוּת."
      },
      {
        "english": "It wanted to be big.",
        "hebrew": "הוּא רָצָה לִהְיוֹת גָּדוֹל."
      },
      {
        "english": "It envied the tall trees.",
        "hebrew": "הוּא קִנֵּא בָּעֵצִים הַגְּבוֹהִים."
      },
      {
        "english": "The wind whispered softly.",
        "hebrew": "הָרוּחַ לָחֲשָׁה חֶרֶשׁ."
      },
      {
        "english": "\"Grow slowly,\" the wind said.",
        "hebrew": "\"גְּדַל לְאַט,\" אָמְרָה הָרוּחַ."
      },
      {
        "english": "The rain gently fell.",
        "hebrew": "הַגֶּשֶׁם יָרַד בְּעַדִינוּת."
      },
      {
        "english": "The sapling drank the water.",
        "hebrew": "הַשָּׁתִיל שָׁתָה אֶת הַמַּיִם."
      },
      {
        "english": "Seasons passed over time.",
        "hebrew": "עוֹנוֹת חָלְפוּ עִם הַזְּמַן."
      },
      {
        "english": "The sapling became a tree.",
        "hebrew": "הַשָּׁתִיל נַעֲשָׂה לְעֵץ."
      },
      {
        "english": "It provided shade and shelter.",
        "hebrew": "הוּא סִפֵּק צֵל וּמַחְסֶה."
      },
      {
        "english": "Animals rested under it.",
        "hebrew": "חַיּוֹת נָחוּ תַחְתָּיו."
      },
      {
        "english": "The tree understood patience.",
        "hebrew": "הָעֵץ הֵבִין מַהִי סַבְלָנוּת."
      },
      {
        "english": "Growth takes time and care.",
        "hebrew": "צְמִיחָה דּוֹרֶשֶׁת זְמַן וְטִפּוּחַ."
      },
      {
        "english": "It was grateful to nature.",
        "hebrew": "הוּא הָיָה אָסִיר תּוֹדָה לַטֶּבַע."
      },
      {
        "english": "The tree stood strong and proud.",
        "hebrew": "הָעֵץ עָמַד חָזָק וְגֵאֶה."
      }
    ]
  },
  "vocabulary": [
    {
      "word": "sapling",
      "translation": "שָּׁתִיל"
    },
    {
      "word": "impatient",
      "translation": "חֲסַר סַבְלָנוּת"
    },
    {
      "word": "envy",
      "translation": "לְקַנֵּא"
    },
    {
      "word": "whisper",
      "translation": "לִלְחוֹשׁ"
    },
    {
      "word": "shelter",
      "translation": "מַחְסֶה"
    },
    {
      "word": "grateful",
      "translation": "אָסִיר תּוֹדָה"
    },
    {
      "word": "growth",
      "translation": "צְמִיחָה"
    }
  ],
  "comprehension_questions": [
    {
      "question": "מָה רָצָה הַשָּׁתִיל בִּתְחִלַּת הַסִּיפּוּר?",
      "options": [
        "לְהִישָּׁאֵר קָטָן",
        "לִהְיוֹת גָּדוֹל כְּמוֹ הָעֵצִים",
        "לַעֲזוֹב אֶת הַיַּעַר"
      ],
      "answer": 1
    },
    {
      "question": "מָה לָמַד הָעֵץ בַּסּוֹף?",
      "options": [
        "שֶׁסַּבְלָנוּת חֲשׁוּבָה לַצְמִיחָה",
        "שֶׁמְהִירוּת הִיא הַמַּפְתֵּחַ",
        "שֶׁגֶּשֶׁם אֵינוֹ טוֹב"
      ],
      "answer": 0
    },
    {
      "question": "מָה סִפֵּק הָעֵץ כְּשֶׁהוּא גָּדַל?",
      "options": [
        "פֵּרוֹת",
        "מַחְסֶה וְצֵל",
        "פְּרָחִים יָפִים"
      ],
      "answer": 1
    }
  ],
  "call_to_action": {
    "text": "הִתְחַבְּרוּ לַטֶּבַע וְלִמְדוּ עוֹד אִתָּנוּ! הֵרָשְׁמוּ עַכְשָׁיו."
  }
}
